[
  {
    "группа": "B63B   1/00",
    "расшифровка": "Гидродинамические или гидростатические характеристики корпусов или подводных крыльев\n            (корпуса подводных лодокB63B   3/13; килиB63B   3/38)",
    "подгруппы": [
      {
        "группа": "B63B   1/02",
        "расшифровка": "обеспечение силы плавучести за счет водоизмещения (1/16имеет преимущество)",
        "подгруппы": [
          {
            "группа": "B63B   1/04",
            "расшифровка": "однокорпусных судов",
            "подгруппы": [
              {
                "группа": "B63B   1/06",
                "расшифровка": "форма носовой части",
                "подгруппы": []
              },
              {
                "группа": "B63B   1/08",
                "расшифровка": "форма кормовой части",
                "подгруппы": []
              }
            ]
          },
          {
            "группа": "B63B   1/10",
            "расшифровка": "многокорпусных судов",
            "подгруппы": [
              {
                "группа": "B63B   1/12",
                "расшифровка": "с жестким соединением корпусов",
                "подгруппы": []
              },
              {
                "группа": "B63B   1/14",
                "расшифровка": "с эластичным соединением корпусов",
                "подгруппы": []
              }
            ]
          }
        ]
      },
      {
        "группа": "B63B   1/16",
        "расшифровка": "обеспечение плавучести за счет дополнительной гидродинамической подъемной силы",
        "подгруппы": [
          {
            "группа": "B63B   1/18",
            "расшифровка": "корпусов глиссерного типа",
            "подгруппы": [
              {
                "группа": "B63B   1/20",
                "расшифровка": "с несколькими глиссирующими поверхностями (1/22имеет преимущество)",
                "подгруппы": []
              },
              {
                "группа": "B63B   1/22",
                "расшифровка": "с изменяемой глиссирующей поверхностью",
                "подгруппы": []
              }
            ]
          },
          {
            "группа": "B63B   1/24",
            "расшифровка": "корпуса с подводными крыльями",
            "подгруппы": [
              {
                "группа": "B63B   1/26",
                "расшифровка": "с двумя и более крыльями (1/28имеет преимущество)",
                "подгруппы": []
              },
              {
                "группа": "B63B   1/28",
                "расшифровка": "подвижными",
                "подгруппы": [
                  {
                    "группа": "B63B   1/30",
                    "расшифровка": "убирающимися или складывающимися",
                    "подгруппы": []
                  }
                ]
              }
            ]
          }
        ]
      },
      {
        "группа": "B63B   1/32",
        "расшифровка": "прочие средства для изменения гидродинамических характеристик корпусов",
        "подгруппы": [
          {
            "группа": "B63B   1/34",
            "расшифровка": "путем уменьшения поверхностного трения",
            "подгруппы": [
              {
                "группа": "B63B   1/36",
                "расшифровка": "с использованием механических средств",
                "подгруппы": []
              },
              {
                "группа": "B63B   1/38",
                "расшифровка": "с использованием пузырьков воздуха или воздушных слоев",
                "подгруппы": []
              }
            ]
          },
          {
            "группа": "B63B   1/40",
            "расшифровка": "путем уменьшения волнового сопротивления",
            "подгруппы": []
          }
        ]
      }
    ]
  },
  {
    "группа": "B63B   3/00",
    "расшифровка": "Конструкции корпусов (неметаллические корпусаB63B   5/00)",
    "подгруппы": [
      {
        "группа": "B63B   3/02",
        "расшифровка": "корпуса, собираемые из предварительно изготовленных секций",
        "подгруппы": [
          {
            "группа": "B63B   3/04",
            "расшифровка": "с неразъемным соединением",
            "подгруппы": [
              {
                "группа": "B63B   3/06",
                "расшифровка": "идентичных секций",
                "подгруппы": []
              }
            ]
          },
          {
            "группа": "B63B   3/08",
            "расшифровка": "с разъемным соединением",
            "подгруппы": []
          }
        ]
      },
      {
        "группа": "B63B   3/09",
        "расшифровка": "корпуса из немагнитного металла",
        "подгруппы": []
      },
      {
        "группа": "B63B   3/10",
        "расшифровка": "бронированные корпуса",
        "подгруппы": []
      },
      {
        "группа": "B63B   3/12",
        "расшифровка": "бескаркасные корпуса",
        "подгруппы": []
      },
      {
        "группа": "B63B   3/13",
        "расшифровка": "корпуса, рассчитанные на гидростатическое давление, при полном их погружении в воду,\n         например корпуса подводных лодок",
        "подгруппы": []
      },
      {
        "группа": "B63B   3/14",
        "расшифровка": "конструктивные элементы корпусов (броня для корпусов3/10)",
        "подгруппы": [
          {
            "группа": "B63B   3/16",
            "расшифровка": "наружная обшивка (иллюминаторы, двери, окна, люки и т.п.19/00)",
            "подгруппы": [
              {
                "группа": "B63B   3/18",
                "расшифровка": "отличающаяся в основном элементами, преобразуемыми в плоские  поверхности",
                "подгруппы": []
              },
              {
                "группа": "B63B   3/20",
                "расшифровка": "двухслойная",
                "подгруппы": []
              },
              {
                "группа": "B63B   3/22",
                "расшифровка": "гофрированная",
                "подгруппы": []
              },
              {
                "группа": "B63B   3/24",
                "расшифровка": "со средствами для уменьшения повреждений при соприкосновении с грунтом, рифами\n         и т.п.",
                "подгруппы": []
              }
            ]
          },
          {
            "группа": "B63B   3/26",
            "расшифровка": "набор корпуса",
            "подгруппы": [
              {
                "группа": "B63B   3/28",
                "расшифровка": "поперечный; стрингеры",
                "подгруппы": [
                  {
                    "группа": "B63B   3/30",
                    "расшифровка": "скуловые кницы; бимсовые кницы",
                    "подгруппы": []
                  }
                ]
              },
              {
                "группа": "B63B   3/32",
                "расшифровка": "рамные шпангоуты; рамные бимсы",
                "подгруппы": []
              },
              {
                "группа": "B63B   3/34",
                "расшифровка": "продольный; присоединения переборок",
                "подгруппы": []
              },
              {
                "группа": "B63B   3/36",
                "расшифровка": "комбинированные системы набора корпуса",
                "подгруппы": []
              }
            ]
          },
          {
            "группа": "B63B   3/38",
            "расшифровка": "кили (выдвижные кили41/00)",
            "подгруппы": []
          },
          {
            "группа": "B63B   3/40",
            "расшифровка": "ахтерштевни; кормовой набор",
            "подгруппы": []
          },
          {
            "группа": "B63B   3/42",
            "расшифровка": "кронштейны гребного вала",
            "подгруппы": []
          },
          {
            "группа": "B63B   3/44",
            "расшифровка": "боковые кили (стабилизирующие пластины39/06)",
            "подгруппы": []
          },
          {
            "группа": "B63B   3/46",
            "расшифровка": "форштевни",
            "подгруппы": []
          },
          {
            "группа": "B63B   3/48",
            "расшифровка": "палубы (настил5/06)",
            "подгруппы": [
              {
                "группа": "B63B   3/50",
                "расшифровка": "сводчатого типа",
                "подгруппы": []
              },
              {
                "группа": "B63B   3/52",
                "расшифровка": "пиллерсы; подпалубные фермы",
                "подгруппы": []
              },
              {
                "группа": "B63B   3/54",
                "расшифровка": "комингсы люков",
                "подгруппы": []
              }
            ]
          },
          {
            "группа": "B63B   3/56",
            "расшифровка": "переборки; конструктивные элементы для усиления переборок  (водонепроницаемые двери43/24)",
            "подгруппы": [
              {
                "группа": "B63B   3/58",
                "расшифровка": "из плоских листов",
                "подгруппы": []
              },
              {
                "группа": "B63B   3/60",
                "расшифровка": "из гофрированных листов",
                "подгруппы": []
              }
            ]
          },
          {
            "группа": "B63B   3/62",
            "расшифровка": "двойное дно; настил второго дна",
            "подгруппы": [
              {
                "группа": "B63B   3/64",
                "расшифровка": "кильсоны",
                "подгруппы": []
              }
            ]
          },
          {
            "группа": "B63B   3/66",
            "расшифровка": "площадки трапов",
            "подгруппы": []
          },
          {
            "группа": "B63B   3/68",
            "расшифровка": "внутренняя отделка; внутренняя обшивка, например с целью изоляции",
            "подгруппы": []
          },
          {
            "группа": "B63B   3/70",
            "расшифровка": "элементы усиления конструкции корпуса под местные нагрузки, например под силовые\n         установки, орудия",
            "подгруппы": []
          }
        ]
      }
    ]
  },
  {
    "группа": "B63B   5/00",
    "расшифровка": "Корпуса из неметаллического материала",
    "подгруппы": [
      {
        "группа": "B63B   5/02",
        "расшифровка": "преимущественно из дерева",
        "подгруппы": [
          {
            "группа": "B63B   5/04",
            "расшифровка": "каркасы",
            "подгруппы": []
          },
          {
            "группа": "B63B   5/06",
            "расшифровка": "палубы; наружная обшивка",
            "подгруппы": [
              {
                "группа": "B63B   5/08",
                "расшифровка": "с однослойным настилом досок",
                "подгруппы": []
              },
              {
                "группа": "B63B   5/10",
                "расшифровка": "с многослойным настилом досок",
                "подгруппы": []
              }
            ]
          }
        ]
      },
      {
        "группа": "B63B   5/12",
        "расшифровка": "преимущественно из дерева с металлическим подкреплением, т.е. композитные конструкции",
        "подгруппы": []
      },
      {
        "группа": "B63B   5/14",
        "расшифровка": "преимущественно из бетона, например железобетонные",
        "подгруппы": [
          {
            "группа": "B63B   5/16",
            "расшифровка": "монолитные",
            "подгруппы": []
          },
          {
            "группа": "B63B   5/18",
            "расшифровка": "собираемые из отдельных секций",
            "подгруппы": [
              {
                "группа": "B63B   5/20",
                "расшифровка": "в сочетании с элементами из других материалов",
                "подгруппы": []
              }
            ]
          },
          {
            "группа": "B63B   5/22",
            "расшифровка": "с усилительными конструктивными элементами снаружи корпуса",
            "подгруппы": []
          }
        ]
      },
      {
        "группа": "B63B   5/24",
        "расшифровка": "преимущественно из пластмассы",
        "подгруппы": []
      }
    ]
  },
  {
    "группа": "B63B   7/00",
    "расшифровка": "Разборные, складные надувные или им подобные суда (разборные, складные или надувные доски для водных видов спортаB63B  32/53; разборные, складные или надувные каноэ, каяки или им подобныеB63B  34/23; складные понтоныB63B  35/36) [2020.01]",
    "подгруппы": [
      {
        "группа": "B63B   7/02",
        "расшифровка": "содержащие только жёсткие части [2020.01]",
        "подгруппы": [
          {
            "группа": "B63B   7/04",
            "расшифровка": "составленные из отдельных секций (доски, составленные из отдельных секций, для водных видов спортаB63B  32/53; составленные из отдельных секций каноэ, каяки или им подобныеB63B  34/23) [2020.01]",
            "подгруппы": []
          }
        ]
      },
      {
        "группа": "B63B   7/06",
        "расшифровка": "имеющие части из нежёсткого материала [2020.01]",
        "подгруппы": [
          {
            "группа": "B63B   7/08",
            "расшифровка": "надувные (надувные доски для водных видов спортаB63B  32/51; надувные каноэ, каяки или им подобные или имеющие надувные частиB63B  34/22) [2020.01]",
            "подгруппы": []
          }
        ]
      }
    ]
  },
  {
    "группа": "B63B  11/00",
    "расшифровка": "Внутреннее подразделение корпусов (конструкция переборок3/56)",
    "подгруппы": [
      {
        "группа": "B63B  11/02",
        "расшифровка": "размещение переборок, например в грузовых трюмах",
        "подгруппы": []
      },
      {
        "группа": "B63B  11/04",
        "расшифровка": "конструкции топливных или балластных цистерн, например с эластичными стенками",
        "подгруппы": []
      },
      {
        "группа": "B63B  11/06",
        "расшифровка": "коридоры (туннели) гребного вала",
        "подгруппы": []
      }
    ]
  },
  {
    "группа": "B63B  13/00",
    "расшифровка": "Балластно-осушительные трубопроводы; самоотливное оборудование; шпигаты",
    "подгруппы": [
      {
        "группа": "B63B  13/02",
        "расшифровка": "порты для выпуска воды",
        "подгруппы": []
      }
    ]
  },
  {
    "группа": "B63B  15/00",
    "расшифровка": "Надстройки;  устройство и расположение мачт",
    "подгруппы": [
      {
        "группа": "B63B  15/02",
        "расшифровка": "крепление мачт и прочих подобных конструкций",
        "подгруппы": []
      }
    ]
  },
  {
    "группа": "B63B  17/00",
    "расшифровка": "Конструктивные элементы и детали корпуса водных транспортных средств, не отнесенные\n            к другим рубрикам",
    "подгруппы": [
      {
        "группа": "B63B  17/02",
        "расшифровка": "тенты, навесы",
        "подгруппы": []
      },
      {
        "группа": "B63B  17/04",
        "расшифровка": "леерные стойки; привальные брусья",
        "подгруппы": []
      },
      {
        "группа": "B63B  17/06",
        "расшифровка": "устройства для удаления отходов, например золы",
        "подгруппы": []
      }
    ]
  },
  {
    "группа": "B63B  19/00",
    "расшифровка": "Устройство и расположение иллюминаторов, дверей, световых люков и прочих проемов и\n            отверстий в корпусе, а также люки и закрытия для них (шпигаты13/00; водонепроницаемые двери в переборках43/24)",
    "подгруппы": [
      {
        "группа": "B63B  19/02",
        "расшифровка": "окна, специально предназначенные для судов или прочих плавучих средств, например\n         смотровые стекла или иллюминаторы",
        "подгруппы": []
      },
      {
        "группа": "B63B  19/04",
        "расшифровка": "воздухоулавливающие устройства для световых люков или иллюминаторов",
        "подгруппы": [
          {
            "группа": "B63B  19/06",
            "расшифровка": "быстросъемные",
            "подгруппы": []
          }
        ]
      },
      {
        "группа": "B63B  19/08",
        "расшифровка": "иллюминаторы или подобные бортовые отверстия судов (порты для выпуска воды через борта судовB63B  13/02)",
        "подгруппы": [
          {
            "группа": "B63B  19/10",
            "расшифровка": "для угольных бункеров",
            "подгруппы": []
          }
        ]
      },
      {
        "группа": "B63B  19/12",
        "расшифровка": "люки; смотровые отверстия (комингсы люков3/54)",
        "подгруппы": [
          {
            "группа": "B63B  19/14",
            "расшифровка": "люковые закрытия",
            "подгруппы": [
              {
                "группа": "B63B  19/16",
                "расшифровка": "со съемными досками",
                "подгруппы": []
              },
              {
                "группа": "B63B  19/18",
                "расшифровка": "скользящие",
                "подгруппы": []
              },
              {
                "группа": "B63B  19/19",
                "расшифровка": "складываемые [3]",
                "подгруппы": [
                  {
                    "группа": "B63B  19/197",
                    "расшифровка": "приводимые в действие давлением текучей среды [3]",
                    "подгруппы": []
                  },
                  {
                    "группа": "B63B  19/203",
                    "расшифровка": "приводимые в действие посредством кабелей, тросов и т.п. [3]",
                    "подгруппы": []
                  }
                ]
              },
              {
                "группа": "B63B  19/21",
                "расшифровка": "свертываемые [3]",
                "подгруппы": []
              }
            ]
          },
          {
            "группа": "B63B  19/22",
            "расшифровка": "люковые бимсы",
            "подгруппы": []
          },
          {
            "группа": "B63B  19/24",
            "расшифровка": "крепления крышек люков, например задрайками",
            "подгруппы": []
          },
          {
            "группа": "B63B  19/26",
            "расшифровка": "уплотнительные элементы; дренажные системы люков",
            "подгруппы": []
          },
          {
            "группа": "B63B  19/28",
            "расшифровка": "прочие защитные устройства",
            "подгруппы": []
          }
        ]
      }
    ]
  },
  {
    "группа": "B63B  21/00",
    "расшифровка": "Оборудование для буксировки; оборудование для толкания, швартовки или перестановки\n            судов; постановка на якорь (динамическая постановка на якорьB63H  25/00) [4]",
    "подгруппы": [
      {
        "группа": "B63B  21/02",
        "расшифровка": "оборудование для магнитной швартовки",
        "подгруппы": []
      },
      {
        "группа": "B63B  21/04",
        "расшифровка": "крепежные или направляющие устройства для цепей, тросов, канатов и подобных элементов",
        "подгруппы": [
          {
            "группа": "B63B  21/06",
            "расшифровка": "кнехты",
            "подгруппы": []
          },
          {
            "группа": "B63B  21/08",
            "расшифровка": "зажимные устройства",
            "подгруппы": []
          },
          {
            "группа": "B63B  21/10",
            "расшифровка": "направляющие проводки снастей, тросов",
            "подгруппы": []
          },
          {
            "группа": "B63B  21/12",
            "расшифровка": "предохранительные приспособления от попадания крыс на суда",
            "подгруппы": []
          },
          {
            "группа": "B63B  21/14",
            "расшифровка": "клюзы; клюзовые трубы; крышки для клюзов",
            "подгруппы": []
          }
        ]
      },
      {
        "группа": "B63B  21/16",
        "расшифровка": "применение лебедок",
        "подгруппы": []
      },
      {
        "группа": "B63B  21/18",
        "расшифровка": "стопоры для якорных цепей",
        "подгруппы": []
      },
      {
        "группа": "B63B  21/20",
        "расшифровка": "применение цепей, канатов, тросов и т.п. и их элементов",
        "подгруппы": []
      },
      {
        "группа": "B63B  21/22",
        "расшифровка": "обращение с якорями, крепление якорей",
        "подгруппы": []
      },
      {
        "группа": "B63B  21/24",
        "расшифровка": "якоря",
        "подгруппы": [
          {
            "группа": "B63B  21/26",
            "расшифровка": "закрепление якорей в грунте",
            "подгруппы": [
              {
                "группа": "B63B  21/27",
                "расшифровка": "путем засасывания [2]",
                "подгруппы": []
              },
              {
                "группа": "B63B  21/28",
                "расшифровка": "путем взрыва заряда",
                "подгруппы": []
              },
              {
                "группа": "B63B  21/29",
                "расшифровка": "под действием веса [2]",
                "подгруппы": []
              }
            ]
          },
          {
            "группа": "B63B  21/30",
            "расшифровка": "с неподвижными лапами [3]",
            "подгруппы": [
              {
                "группа": "B63B  21/32",
                "расшифровка": "с одной лапой",
                "подгруппы": []
              },
              {
                "группа": "B63B  21/34",
                "расшифровка": "с двумя и более лапами",
                "подгруппы": [
                  {
                    "группа": "B63B  21/36",
                    "расшифровка": "складными",
                    "подгруппы": []
                  }
                ]
              }
            ]
          },
          {
            "группа": "B63B  21/38",
            "расшифровка": "с поворотными лапами [3]",
            "подгруппы": [
              {
                "группа": "B63B  21/40",
                "расшифровка": "с одной лапой",
                "подгруппы": [
                  {
                    "группа": "B63B  21/42",
                    "расшифровка": "лемешного типа",
                    "подгруппы": []
                  }
                ]
              },
              {
                "группа": "B63B  21/44",
                "расшифровка": "с двумя и более лапами",
                "подгруппы": []
              }
            ]
          },
          {
            "группа": "B63B  21/46",
            "расшифровка": "со скользящим соединением с цепью [2]",
            "подгруппы": []
          },
          {
            "группа": "B63B  21/48",
            "расшифровка": "морские якоря;  плавучие якоря",
            "подгруппы": []
          }
        ]
      },
      {
        "группа": "B63B  21/50",
        "расшифровка": "якорные устройства для водных транспортных средств специального назначения, например\n         для плавучих бурильных платформ или землесосных снарядов",
        "подгруппы": []
      },
      {
        "группа": "B63B  21/54",
        "расшифровка": "отпорные крюки и подобные устройства",
        "подгруппы": []
      },
      {
        "группа": "B63B  21/56",
        "расшифровка": "тянущее или толкающее оборудование для буксировки (буксиры35/66)",
        "подгруппы": [
          {
            "группа": "B63B  21/58",
            "расшифровка": "гаки для буксировки; крепление буксирных гаков",
            "подгруппы": [
              {
                "группа": "B63B  21/60",
                "расшифровка": "быстрорасцепляющиеся",
                "подгруппы": []
              }
            ]
          },
          {
            "группа": "B63B  21/62",
            "расшифровка": "для буксировки нескольких судов",
            "подгруппы": []
          },
          {
            "группа": "B63B  21/64",
            "расшифровка": "с помощью транспортных средств или живой силы, передвигающихся  по сухопутным дорогам,\n         проложенным вдоль водного пути (багры и подобные устройства21/54)",
            "подгруппы": []
          },
          {
            "группа": "B63B  21/66",
            "расшифровка": "оборудование, специально предназначенное для буксировки объектов или судов, находящихся\n         под водой, например обтекатели для буксирных тросов [3]",
            "подгруппы": []
          }
        ]
      }
    ]
  },
  {
    "группа": "B63B  22/00",
    "расшифровка": "Буи, бакены (средства для указания местонахождения объектов под водойB 63C   7/26; спасательные плавучие средства, например кругиB 63C   9/08) [4]",
    "подгруппы": [
      {
        "группа": "B63B  22/02",
        "расшифровка": "специально приспособленные для причаливания к ним судна [4]",
        "подгруппы": []
      },
      {
        "группа": "B63B  22/04",
        "расшифровка": "якорные устройства [4]",
        "подгруппы": [
          {
            "группа": "B63B  22/06",
            "расшифровка": "со средствами для направления буя к поверхности в ответ на переданный сигнал [4]",
            "подгруппы": []
          },
          {
            "группа": "B63B  22/08",
            "расшифровка": "со средствами для отделения буя или удержания его на поверхности при его погружении,\n         например для обозначения местонахождения затонувшего объекта [4]",
            "подгруппы": [
              {
                "группа": "B63B  22/10",
                "расшифровка": "средства, растворимые в воде или теряющие прочность под влиянием воды, т.е. буи,\n         отделяющиеся от средств, соединяющих буй с объектом, путем их разрушения при контакте\n         с водой [4]",
                "подгруппы": []
              },
              {
                "группа": "B63B  22/12",
                "расшифровка": "удерживающими буй на поверхности с помощью газа, выделяющегося или образующегося\n         при погружении буя [4]",
                "подгруппы": []
              },
              {
                "группа": "B63B  22/14",
                "расшифровка": "средства, соединяющие буй с объектом, чувствительные к гидростатическому давлению\n         [4]",
                "подгруппы": []
              }
            ]
          }
        ]
      },
      {
        "группа": "B63B  22/16",
        "расшифровка": "специально предназначенные для обозначения навигационного пути  [4]",
        "подгруппы": []
      },
      {
        "группа": "B63B  22/18",
        "расшифровка": "со средствами для управления положением, например реактивные поверхности или связи\n         [4]",
        "подгруппы": [
          {
            "группа": "B63B  22/20",
            "расшифровка": "балластные средства [4]",
            "подгруппы": []
          }
        ]
      },
      {
        "группа": "B63B  22/22",
        "расшифровка": "надувные буи с газогенераторными средствами (B63B  22/12имеет преимущество) [4]",
        "подгруппы": []
      },
      {
        "группа": "B63B  22/24",
        "расшифровка": "контейнерного типа, т.е. обеспечивающие хранение материала [4]",
        "подгруппы": [
          {
            "группа": "B63B  22/26",
            "расшифровка": "со средствами для избирательного освобождения емкостей, например с вертлюжными соединениями\n         [4]",
            "подгруппы": []
          },
          {
            "группа": "B63B  22/28",
            "расшифровка": "погруженные в воду, когда не используются [4]",
            "подгруппы": []
          }
        ]
      }
    ]
  },
  {
    "группа": "B63B  23/00",
    "расшифровка": "Шлюпочные устройства",
    "подгруппы": [
      {
        "группа": "B63B  23/02",
        "расшифровка": "шлюпочные устройства с кронштейнами для спуска шлюпок на канатах",
        "подгруппы": [
          {
            "группа": "B63B  23/04",
            "расшифровка": "поворотные относительно горизонтальной оси вращения, например гравитационного типа",
            "подгруппы": [
              {
                "группа": "B63B  23/06",
                "расшифровка": "с фактически имеющейся осью вращения",
                "подгруппы": [
                  {
                    "группа": "B63B  23/08",
                    "расшифровка": "с шарнирными шлюпбалками",
                    "подгруппы": []
                  },
                  {
                    "группа": "B63B  23/10",
                    "расшифровка": "с принудительным движением шлюпбалок",
                    "подгруппы": []
                  }
                ]
              },
              {
                "группа": "B63B  23/12",
                "расшифровка": "с фиктивной осью вращения",
                "подгруппы": [
                  {
                    "группа": "B63B  23/14",
                    "расшифровка": "с использованием тяг",
                    "подгруппы": []
                  },
                  {
                    "группа": "B63B  23/16",
                    "расшифровка": "с использованием направляющей колеи",
                    "подгруппы": []
                  }
                ]
              }
            ]
          },
          {
            "группа": "B63B  23/18",
            "расшифровка": "поворотные относительно вертикальной оси вращения",
            "подгруппы": [
              {
                "группа": "B63B  23/20",
                "расшифровка": "с одиночной шлюпбалкой",
                "подгруппы": [
                  {
                    "группа": "B63B  23/22",
                    "расшифровка": "стропы или подобные устройства",
                    "подгруппы": []
                  }
                ]
              },
              {
                "группа": "B63B  23/24",
                "расшифровка": "поворотные устройства для них",
                "подгруппы": []
              }
            ]
          },
          {
            "группа": "B63B  23/26",
            "расшифровка": "заваливающиеся (откидные)",
            "подгруппы": []
          }
        ]
      },
      {
        "группа": "B63B  23/28",
        "расшифровка": "устройства, освобождающие шлюпку или выдвигающие ее за борт для  свободного сброса\n         на воду",
        "подгруппы": []
      },
      {
        "группа": "B63B  23/30",
        "расшифровка": "устройства для направления шлюпок к поверхности воды",
        "подгруппы": [
          {
            "группа": "B63B  23/32",
            "расшифровка": "жесткие направляющие, например со штангами, поворачиваемыми около ватерлинии",
            "подгруппы": []
          },
          {
            "группа": "B63B  23/34",
            "расшифровка": "направляющие устройства для спуска с помощью тросов, например при крене судна",
            "подгруппы": [
              {
                "группа": "B63B  23/36",
                "расшифровка": "скользящие упорные брусья",
                "подгруппы": []
              }
            ]
          }
        ]
      },
      {
        "группа": "B63B  23/38",
        "расшифровка": "транспортировка шлюпок к шлюпбалкам или подобным устройствам",
        "подгруппы": []
      },
      {
        "группа": "B63B  23/40",
        "расшифровка": "применение механизмов для подъема или спуска шлюпок",
        "подгруппы": [
          {
            "группа": "B63B  23/42",
            "расшифровка": "с тормозными устройствами",
            "подгруппы": [
              {
                "группа": "B63B  23/44",
                "расшифровка": "на судне",
                "подгруппы": []
              },
              {
                "группа": "B63B  23/46",
                "расшифровка": "на шлюпке",
                "подгруппы": []
              }
            ]
          },
          {
            "группа": "B63B  23/48",
            "расшифровка": "применение лебедок для манипулирования шлюпками",
            "подгруппы": [
              {
                "группа": "B63B  23/50",
                "расшифровка": "с натяжными устройствами",
                "подгруппы": []
              },
              {
                "группа": "B63B  23/52",
                "расшифровка": "с управлением лебедками со шлюпки",
                "подгруппы": []
              }
            ]
          },
          {
            "группа": "B63B  23/54",
            "расшифровка": "с устройствами для дифферентовки",
            "подгруппы": [
              {
                "группа": "B63B  23/56",
                "расшифровка": "управляемыми со шлюпки",
                "подгруппы": []
              }
            ]
          },
          {
            "группа": "B63B  23/58",
            "расшифровка": "с устройствами для зацепления или расцепления с передаточным  механизмом",
            "подгруппы": []
          },
          {
            "группа": "B63B  23/60",
            "расшифровка": "с дополнительными соединениями между шлюпкой и шлюпбалкой",
            "подгруппы": []
          }
        ]
      },
      {
        "группа": "B63B  23/62",
        "расшифровка": "крепление или хранение шлюпок на палубе",
        "подгруппы": [
          {
            "группа": "B63B  23/64",
            "расшифровка": "найтовы; чехлы для шлюпок",
            "подгруппы": []
          },
          {
            "группа": "B63B  23/66",
            "расшифровка": "блоки; клинья",
            "подгруппы": [
              {
                "группа": "B63B  23/68",
                "расшифровка": "для постановки шлюпок в два яруса",
                "подгруппы": []
              }
            ]
          }
        ]
      },
      {
        "группа": "B63B  23/70",
        "расшифровка": "погрузочно-разгрузочное оборудование, реагирующее на определенные условия, например\n         автоматически отделяющее лодку от талей для спуска в момент соприкосновения с водой\n         [4]",
        "подгруппы": []
      }
    ]
  },
  {
    "группа": "B63B  25/00",
    "расшифровка": "Способы и устройства для размещения грузов, например штивка грузов, или размещение\n            грузов в трюме; суда, характеризующиеся наличием таких устройств (рыбные трюмы рыболовецких судовB63B  35/24; размещения грузов иначе, чем в грузовом отсеке, например с помощью балласта,B63B  43/06;B63B  43/08)",
    "подгруппы": [
      {
        "группа": "B63B  25/02",
        "расшифровка": "массовых грузов",
        "подгруппы": [
          {
            "группа": "B63B  25/04",
            "расшифровка": "твердых",
            "подгруппы": [
              {
                "группа": "B63B  25/06",
                "расшифровка": "зерна",
                "подгруппы": []
              }
            ]
          },
          {
            "группа": "B63B  25/08",
            "расшифровка": "жидких",
            "подгруппы": [
              {
                "группа": "B63B  25/10",
                "расшифровка": "в открытых отсеках или резервуарах",
                "подгруппы": []
              },
              {
                "группа": "B63B  25/12",
                "расшифровка": "в закрытых цистернах (танках)",
                "подгруппы": [
                  {
                    "группа": "B63B  25/14",
                    "расшифровка": "находящихся под давлением",
                    "подгруппы": []
                  },
                  {
                    "группа": "B63B  25/16",
                    "расшифровка": "с теплоизоляцией",
                    "подгруппы": []
                  }
                ]
              }
            ]
          }
        ]
      },
      {
        "группа": "B63B  25/18",
        "расшифровка": "разборные палубы",
        "подгруппы": [
          {
            "группа": "B63B  25/20",
            "расшифровка": "для самоходных судов и т.п.",
            "подгруппы": []
          }
        ]
      },
      {
        "группа": "B63B  25/22",
        "расшифровка": "штабелируемых грузов",
        "подгруппы": []
      },
      {
        "группа": "B63B  25/24",
        "расшифровка": "средства для предотвращения нежелательных перемещений грузов, например прокладки",
        "подгруппы": []
      },
      {
        "группа": "B63B  25/26",
        "расшифровка": "замороженных грузов",
        "подгруппы": []
      },
      {
        "группа": "B63B  25/28",
        "расшифровка": "палубных грузов",
        "подгруппы": []
      }
    ]
  },
  {
    "группа": "B63B  27/00",
    "расшифровка": "Размещение корабельного оборудования для погрузки и разгрузки грузов или пассажиров\n            (саморазгружающиеся баржи или лихтеры35/30; плавучие краныB66C  23/52) [3]",
    "подгруппы": [
      {
        "группа": "B63B  27/04",
        "расшифровка": "деррик-кранов  [3]",
        "подгруппы": []
      },
      {
        "группа": "B63B  27/08",
        "расшифровка": "лебедок [3]",
        "подгруппы": []
      },
      {
        "группа": "B63B  27/10",
        "расшифровка": "подъемных кранов [3]",
        "подгруппы": [
          {
            "группа": "B63B  27/12",
            "расшифровка": "портального (козлового) типа [3]",
            "подгруппы": []
          }
        ]
      },
      {
        "группа": "B63B  27/14",
        "расшифровка": "наклонных погрузочных платформ, сходней или бортовых трапов [3]",
        "подгруппы": []
      },
      {
        "группа": "B63B  27/16",
        "расшифровка": "лифтов или других подъемников [3]",
        "подгруппы": []
      },
      {
        "группа": "B63B  27/18",
        "расшифровка": "подвесных трапов, например со спасательными беседками для снятия людей с аварийного\n         судна [3]",
        "подгруппы": []
      },
      {
        "группа": "B63B  27/22",
        "расшифровка": "конвейеров, например ленточных или шнековых [3,6]",
        "подгруппы": []
      },
      {
        "группа": "B63B  27/24",
        "расшифровка": "трубопроводов [3]",
        "подгруппы": [
          {
            "группа": "B63B  27/25",
            "расшифровка": "для материалов в виде жидкотекучей массы [3]",
            "подгруппы": []
          }
        ]
      },
      {
        "группа": "B63B  27/26",
        "расшифровка": "устройств бросательного действия [3]",
        "подгруппы": []
      },
      {
        "группа": "B63B  27/28",
        "расшифровка": "желобов [3]",
        "подгруппы": []
      },
      {
        "группа": "B63B  27/30",
        "расшифровка": "для передачи груза над морем с судна на судно или с судна на удаленный от берега\n         объект [3]",
        "подгруппы": [
          {
            "группа": "B63B  27/32",
            "расшифровка": "с использованием кабелькранов [3]",
            "подгруппы": []
          },
          {
            "группа": "B63B  27/34",
            "расшифровка": "с использованием трубопроводов [3]",
            "подгруппы": []
          }
        ]
      },
      {
        "группа": "B63B  27/36",
        "расшифровка": "для плавучих грузов [3]",
        "подгруппы": []
      }
    ]
  },
  {
    "группа": "B63B  29/00",
    "расшифровка": "Помещения для членов экипажа или пассажиров, не отнесенные к другим рубрикам",
    "подгруппы": [
      {
        "группа": "B63B  29/02",
        "расшифровка": "каюты и прочие жилые помещения; их конструкция и расположение",
        "подгруппы": [
          {
            "группа": "B63B  29/04",
            "расшифровка": "мебель, специально предназначенная для судов",
            "подгруппы": [
              {
                "группа": "B63B  29/06",
                "расшифровка": "прикрепление к полу",
                "подгруппы": []
              },
              {
                "группа": "B63B  29/08",
                "расшифровка": "штормовые защитные устройства на столах, например штормовые планки",
                "подгруппы": []
              },
              {
                "группа": "B63B  29/10",
                "расшифровка": "койки; коечные трапы",
                "подгруппы": []
              },
              {
                "группа": "B63B  29/12",
                "расшифровка": "самоуравнивающиеся опорные устройства",
                "подгруппы": []
              }
            ]
          },
          {
            "группа": "B63B  29/14",
            "расшифровка": "санитарные узлы; судовое оборудование для умывальников или ванн",
            "подгруппы": []
          }
        ]
      },
      {
        "группа": "B63B  29/16",
        "расшифровка": "устройства для удаления мусора и воды",
        "подгруппы": []
      },
      {
        "группа": "B63B  29/18",
        "расшифровка": "устройство и расположение плавательных бассейнов",
        "подгруппы": []
      },
      {
        "группа": "B63B  29/20",
        "расшифровка": "трапы (коечные трапы29/10)",
        "подгруппы": []
      },
      {
        "группа": "B63B  29/22",
        "расшифровка": "камбузы [2]",
        "подгруппы": []
      }
    ]
  },
  {
    "группа": "B63B  32/00",
    "расшифровка": "Доски для водных видов спорта; аксессуары для них [2020.01]",
    "подгруппы": [
      {
        "группа": "B63B  32/10",
        "расшифровка": "моторизованные доски для водных видов спорта (персональные плавучие средства с силовым приводомB63B  34/10) [2020.01]",
        "подгруппы": []
      },
      {
        "группа": "B63B  32/20",
        "расшифровка": "доски, специально предназначенные для использования в лежачем положении, например\n         сани для водного бурного потока (буксируемые водные саниB63B  34/54) [2020.01]",
        "подгруппы": [
          {
            "группа": "B63B  32/22",
            "расшифровка": "доски для буги-сёрфинга; аксессуары, специально предназначенные для них [2020.01]",
            "подгруппы": []
          }
        ]
      },
      {
        "группа": "B63B  32/30",
        "расшифровка": "водные лыжи, прикреплённые к ногам пользователя; аксессуары, специально предназначенные\n         для них [2020.01]",
        "подгруппы": []
      },
      {
        "группа": "B63B  32/40",
        "расшифровка": "доски с двумя наконечниками; доски для катания за катером; доски для сёрфинга; доски\n         для виндсёрфинга, вёсельные доски, например доски  [SUP]; аксессуары, специально предназначенные\n         для них [2020.01]",
        "подгруппы": []
      },
      {
        "группа": "B63B  32/50",
        "расшифровка": "доски, характеризующиеся их конструктивными особенностями [2020.01]",
        "подгруппы": [
          {
            "группа": "B63B  32/51",
            "расшифровка": "надувные доски, например шероховатые надувные доски [2020.01]",
            "подгруппы": []
          },
          {
            "группа": "B63B  32/53",
            "расшифровка": "доски, составленные из отдельных секций, например модульные, разборные или складные\n         [2020.01]",
            "подгруппы": []
          },
          {
            "группа": "B63B  32/55",
            "расшифровка": "многокорпусные суда, например типа катамарана [2020.01]",
            "подгруппы": []
          },
          {
            "группа": "B63B  32/56",
            "расшифровка": "доски, преобразуемые в суда или другие типы досок для водных видов спорта, например\n         в парусные лодки, каноэ или водные велосипеды [2020.01]",
            "подгруппы": []
          }
        ]
      },
      {
        "группа": "B63B  32/57",
        "расшифровка": "доски, характеризующиеся материалом, например слоистыми материалами [2020.01]",
        "подгруппы": []
      },
      {
        "группа": "B63B  32/59",
        "расшифровка": "доски, характеризующиеся их способом производства, например литые или изготовленные\n         способом трёхмерной печати [2020.01]",
        "подгруппы": []
      },
      {
        "группа": "B63B  32/60",
        "расшифровка": "выступающие части досок, например плавники, гидрокрылья или выдвижные кили [2020.01]",
        "подгруппы": [
          {
            "группа": "B63B  32/62",
            "расшифровка": "характеризующиеся материалом, например слоистыми материалами; характеризующиеся\n         их способом изготовления [2020.01]",
            "подгруппы": []
          },
          {
            "группа": "B63B  32/64",
            "расшифровка": "регулируемые, например добавлением секций, удалением секций или изменением  установки\n         или профиля [2020.01]",
            "подгруппы": []
          },
          {
            "группа": "B63B  32/66",
            "расшифровка": "средства фиксации к доскам, например муфты плавников или муфты крыльев [2020.01]",
            "подгруппы": []
          }
        ]
      },
      {
        "группа": "B63B  32/68",
        "расшифровка": "крепления  основания мачт, например перекладины основания мачт [2020.01]",
        "подгруппы": []
      },
      {
        "группа": "B63B  32/70",
        "расшифровка": "аксессуары, специально не предназначенные для отдельных видов досок, например обшивочные\n         элементы или элементы создания плавучести [2020.01]",
        "подгруппы": [
          {
            "группа": "B63B  32/73",
            "расшифровка": "для привязывания пользователей или предметов к доске, например ремни [2020.01]",
            "подгруппы": []
          }
        ]
      },
      {
        "группа": "B63B  32/77",
        "расшифровка": "устройства для фиксации аксессуаров к доске, например вставки или рельсы [2020.01]",
        "подгруппы": []
      },
      {
        "группа": "B63B  32/80",
        "расшифровка": "устройства, специально предназначенные для хранения или транспортировки досок для\n         водных видов спорта [2020.01]",
        "подгруппы": [
          {
            "группа": "B63B  32/83",
            "расшифровка": "для хранения, например стеллажи или стропы [2020.01]",
            "подгруппы": []
          },
          {
            "группа": "B63B  32/87",
            "расшифровка": "для переноски, например чехлы для досок [2020.01]",
            "подгруппы": []
          }
        ]
      }
    ]
  },
  {
    "группа": "B63B  34/00",
    "расшифровка": "Суда, специально предназначенные для водных видов спорта; устройства для поддержки\n            тела, специально предназначенные для водных видов спорта или досуга (доски для водных видов спортаB63B  32/00; плавающие аппаратыA63B  35/00; оборудование для осуществления движения   с помощью мускульной силыB63H  16/00) [2020.01]",
    "подгруппы": [
      {
        "группа": "B63B  34/10",
        "расшифровка": "личные суда с приводом от собственного двигателя, например водные скутеры (водяные реактивные движителиB63H  11/00; управление струйными рулямиB63H  25/46); аксессуары для них [2020.01]",
        "подгруппы": [
          {
            "группа": "B63B  34/15",
            "расшифровка": "для видов спорта, относящихся к полётам с помощью водяных струй  [2020.01]",
            "подгруппы": []
          }
        ]
      },
      {
        "группа": "B63B  34/20",
        "расшифровка": "каноэ, каяки или им подобные [2020.01]",
        "подгруппы": [
          {
            "группа": "B63B  34/21",
            "расшифровка": "характеризующиеся конструктивными особенностями [2020.01]",
            "подгруппы": [
              {
                "группа": "B63B  34/22",
                "расшифровка": "надувные; имеющие надувные части [2020.01]",
                "подгруппы": []
              },
              {
                "группа": "B63B  34/23",
                "расшифровка": "составленные из отдельных секций, например модульные, разборные или складные [2020.01]",
                "подгруппы": []
              }
            ]
          }
        ]
      },
      {
        "группа": "B63B  34/26",
        "расшифровка": "аксессуары для каноэ, каяков или подобных им (осуществление движения за счёт мускульной силыB63H  16/00; забортные движительные агрегатыB63H  20/00) [2020.01]",
        "подгруппы": []
      },
      {
        "группа": "B63B  34/30",
        "расшифровка": "вёсельные лодки, специально предназначенные для гонок; аксессуары дл них (осуществление движения за счёт греблиB63H  16/00) [2020.01]",
        "подгруппы": []
      },
      {
        "группа": "B63B  34/40",
        "расшифровка": "конструкция для поддержки тела, поддерживаемые в динамическом режиме с помощью подводных\n         крыльев [2020.01]",
        "подгруппы": [
          {
            "группа": "B63B  34/45",
            "расшифровка": "аксессуары для них [2020.01]",
            "подгруппы": []
          }
        ]
      },
      {
        "группа": "B63B  34/50",
        "расшифровка": "плавающие устройства для поддержки  тела, например лодки для купания или водные велосипеды\n         (вспомогательные средства для плаванияA63B  31/00) [2020.01]",
        "подгруппы": [
          {
            "группа": "B63B  34/52",
            "расшифровка": "или частично надувные [2020.01]",
            "подгруппы": []
          },
          {
            "группа": "B63B  34/54",
            "расшифровка": "специально предназначенные для буксировки, например надувные бананы, водные сани\n         или буксируемые буи (устройства для буксировкиB63B  34/60) [2020.01]",
            "подгруппы": []
          },
          {
            "группа": "B63B  34/56",
            "расшифровка": "для использования в положении стоя, например коралловые тапочки, устройства для\n         ходьбы по воде или плавучие лыжи [2020.01]",
            "подгруппы": []
          },
          {
            "группа": "B63B  34/565",
            "расшифровка": "аксессуары, например палки для ходьбы на воде [2020.01]",
            "подгруппы": []
          }
        ]
      },
      {
        "группа": "B63B  34/60",
        "расшифровка": "устройства для буксировки, например для использования с водными лыжами или досками\n         для катания за катером [2020.01]",
        "подгруппы": [
          {
            "группа": "B63B  34/63",
            "расшифровка": "средства удерживания пользователя,  например рули или привязная система [2020.01]",
            "подгруппы": []
          },
          {
            "группа": "B63B  34/67",
            "расшифровка": "средства соединения на буксирующем судне, например стойки, боковые опоры или лебёдки\n         [2020.01]",
            "подгруппы": []
          }
        ]
      },
      {
        "группа": "B63B  34/70",
        "расшифровка": "устройства на судах, специально предназначенные для генерирования волн для сёрфинга,\n         катания на доске за катером или т.п., например балластные баки [2020.01]",
        "подгруппы": [
          {
            "группа": "B63B  34/75",
            "расшифровка": "расположение пластин для кильватерной струи [2020.01]",
            "подгруппы": []
          }
        ]
      }
    ]
  },
  {
    "группа": "B63B  35/00",
    "расшифровка": "Суда или подобные плавучие сооружения, специально предназначенные для особых целей,\n            и не относящиеся к другим группам [2020.01]",
    "подгруппы": [
      {
        "группа": "B63B  35/03",
        "расшифровка": "суда для прокладки труб [5]",
        "подгруппы": []
      },
      {
        "группа": "B63B  35/04",
        "расшифровка": "суда для прокладки кабелей [5]",
        "подгруппы": [
          {
            "группа": "B63B  35/06",
            "расшифровка": "с устройствами для перемещения концов каната от судна на берег [5]",
            "подгруппы": []
          }
        ]
      },
      {
        "группа": "B63B  35/08",
        "расшифровка": "ледоколы [5]",
        "подгруппы": [
          {
            "группа": "B63B  35/10",
            "расшифровка": "с устройствами для обеспечения килевой или бортовой качки [5]",
            "подгруппы": []
          },
          {
            "группа": "B63B  35/12",
            "расшифровка": "с устройствами для резки льда [5]",
            "подгруппы": []
          }
        ]
      },
      {
        "группа": "B63B  35/14",
        "расшифровка": "рыболовные суда [5]",
        "подгруппы": [
          {
            "группа": "B63B  35/16",
            "расшифровка": "траулеры [5]",
            "подгруппы": [
              {
                "группа": "B63B  35/18",
                "расшифровка": "с устройствами для буксировки сетей за бортом [5]",
                "подгруппы": []
              },
              {
                "группа": "B63B  35/20",
                "расшифровка": "с устройствами для подъема сетей на борт [5]",
                "подгруппы": []
              }
            ]
          },
          {
            "группа": "B63B  35/22",
            "расшифровка": "китобойные суда; китобойные перерабатывающие базы [5]",
            "подгруппы": []
          },
          {
            "группа": "B63B  35/24",
            "расшифровка": "суда с трюмами, приспособленными для хранения рыбы [5]",
            "подгруппы": [
              {
                "группа": "B63B  35/26",
                "расшифровка": "живой [5]",
                "подгруппы": []
              }
            ]
          }
        ]
      },
      {
        "группа": "B63B  35/28",
        "расшифровка": "баржи или лихтеры [5]",
        "подгруппы": [
          {
            "группа": "B63B  35/30",
            "расшифровка": "саморазгружающиеся [5]",
            "подгруппы": []
          }
        ]
      },
      {
        "группа": "B63B  35/32",
        "расшифровка": "для сбора загрязнений с поверхности открытых водоемов [5]",
        "подгруппы": []
      },
      {
        "группа": "B63B  35/34",
        "расшифровка": "понтоны [5]",
        "подгруппы": [
          {
            "группа": "B63B  35/36",
            "расшифровка": "складываемые [5]",
            "подгруппы": []
          },
          {
            "группа": "B63B  35/38",
            "расшифровка": "жестко соединенные между собой [5]",
            "подгруппы": []
          }
        ]
      },
      {
        "группа": "B63B  35/40",
        "расшифровка": "для транспортировки морских судов [5]",
        "подгруппы": [
          {
            "группа": "B63B  35/42",
            "расшифровка": "с регулируемой осадкой [5]",
            "подгруппы": []
          }
        ]
      },
      {
        "группа": "B63B  35/44",
        "расшифровка": "плавучие сооружения, склады, буровые платформы, мастерские, например снабженные устройствами\n         для отделения воды от нефти или масла [5]",
        "подгруппы": []
      },
      {
        "группа": "B63B  35/50",
        "расшифровка": "суда или плавучие устройства для самолетов (авианосцыB63G  11/00) [5]",
        "подгруппы": [
          {
            "группа": "B63B  35/52",
            "расшифровка": "сети, плавучие эллинги и т.п. для извлечения самолета из воды [5]",
            "подгруппы": []
          },
          {
            "группа": "B63B  35/53",
            "расшифровка": "плавучие взлетно-посадочные площадки [3,5]",
            "подгруппы": []
          }
        ]
      },
      {
        "группа": "B63B  35/54",
        "расшифровка": "паромы [5]",
        "подгруппы": []
      },
      {
        "группа": "B63B  35/56",
        "расшифровка": "плавучие маяки (обозначение фарватеров и опасных мест на водных путях51/00) [5]",
        "подгруппы": []
      },
      {
        "группа": "B63B  35/58",
        "расшифровка": "плоты, т.е. плавучие сооружения, которые свободно плавают с небольшой осадкой при\n         малом или отсутствующем надводном борте и имеют платформу или настил для поддерживания\n         пользователя (спасательные плоты и подобные устройстваB63C   9/02) [4,5]",
        "подгруппы": [
          {
            "группа": "B63B  35/607",
            "расшифровка": "с платформой или настилом, расположенным ниже уровня плавучего средства, например\n         типа подвесной корзины [4,5]",
            "подгруппы": []
          },
          {
            "группа": "B63B  35/613",
            "расшифровка": "с плавучими элементами трубчатой формы [4,5]",
            "подгруппы": []
          },
          {
            "группа": "B63B  35/62",
            "расшифровка": "образованные из бревен и т.п. [4,5]",
            "подгруппы": []
          }
        ]
      },
      {
        "группа": "B63B  35/66",
        "расшифровка": "буксиры [5]",
        "подгруппы": [
          {
            "группа": "B63B  35/68",
            "расшифровка": "тянущие [5]",
            "подгруппы": []
          },
          {
            "группа": "B63B  35/70",
            "расшифровка": "толкающие [5]",
            "подгруппы": []
          }
        ]
      }
    ]
  },
  {
    "группа": "B63B  39/00",
    "расшифровка": "Способы и устройства для уменьшения килевой и бортовой качки или подобных нежелательных\n            движений водных транспортных средств; аппаратура для определения положения (осадки,\n            крена) судна на воде",
    "подгруппы": [
      {
        "группа": "B63B  39/02",
        "расшифровка": "путем перемещения грузов [2]",
        "подгруппы": [
          {
            "группа": "B63B  39/03",
            "расшифровка": "жидкостей [2]",
            "подгруппы": []
          }
        ]
      },
      {
        "группа": "B63B  39/04",
        "расшифровка": "с помощью гироскопов",
        "подгруппы": []
      },
      {
        "группа": "B63B  39/06",
        "расшифровка": "с помощью стабилизирующих пластин, воздействующих на воду (боковые кили3/44)",
        "подгруппы": []
      },
      {
        "группа": "B63B  39/08",
        "расшифровка": "с помощью реактивных струй или гребных винтов (применение реактивных струй или гребных винтов для управления судами или постановки\n         на якорьB 63H  25/00)",
        "подгруппы": []
      },
      {
        "группа": "B63B  39/10",
        "расшифровка": "путем демпфирования волн, например путем создания масляной пленки на поверхности\n         воды вокруг судна [2]",
        "подгруппы": []
      },
      {
        "группа": "B63B  39/12",
        "расшифровка": "для определения осадки или нагрузки",
        "подгруппы": []
      },
      {
        "группа": "B63B  39/14",
        "расшифровка": "для определения крена или периода качки",
        "подгруппы": []
      }
    ]
  },
  {
    "группа": "B63B  41/00",
    "расшифровка": "Выдвижные кили, например центральные или бортовые (кили в качестве элемента набора корпуса3/38; стабилизирующие пластины39/06)",
    "подгруппы": []
  },
  {
    "группа": "B63B  43/00",
    "расшифровка": "Средства, повышающие безопасность плавания водных транспортных средств, например средства\n            борьбы за живучесть судна, не отнесенные  к другим рубрикам",
    "подгруппы": [
      {
        "группа": "B63B  43/02",
        "расшифровка": "уменьшающие опасность опрокидывания или затопления (с помощью водонепроницаемых дверей в переборках43/24)",
        "подгруппы": [
          {
            "группа": "B63B  43/04",
            "расшифровка": "путем улучшения остойчивости",
            "подгруппы": [
              {
                "группа": "B63B  43/06",
                "расшифровка": "с использованием балластных цистерн",
                "подгруппы": []
              },
              {
                "группа": "B63B  43/08",
                "расшифровка": "путем перемещения твердого балласта",
                "подгруппы": []
              }
            ]
          },
          {
            "группа": "B63B  43/10",
            "расшифровка": "путем улучшения плавучести",
            "подгруппы": [
              {
                "группа": "B63B  43/12",
                "расшифровка": "с использованием внутренних воздушных емкостей",
                "подгруппы": []
              },
              {
                "группа": "B63B  43/14",
                "расшифровка": "с использованием забортных плавающих элементов",
                "подгруппы": []
              },
              {
                "группа": "B63B  43/16",
                "расшифровка": "аварийное оборудование для остановки течи, например маты или  пластыри",
                "подгруппы": []
              }
            ]
          }
        ]
      },
      {
        "группа": "B63B  43/18",
        "расшифровка": "предупреждающие столкновение; уменьшающие размеры повреждения судна при столкновении",
        "подгруппы": [
          {
            "группа": "B63B  43/20",
            "расшифровка": "чувствительные элементы (датчики)",
            "подгруппы": []
          }
        ]
      },
      {
        "группа": "B63B  43/24",
        "расшифровка": "водонепроницаемые двери в переборках",
        "подгруппы": [
          {
            "группа": "B63B  43/26",
            "расшифровка": "скользящие",
            "подгруппы": [
              {
                "группа": "B63B  43/28",
                "расшифровка": "с механическим приводом",
                "подгруппы": []
              },
              {
                "группа": "B63B  43/30",
                "расшифровка": "с пневматическим или гидравлическим приводом",
                "подгруппы": []
              }
            ]
          },
          {
            "группа": "B63B  43/32",
            "расшифровка": "нескользящие",
            "подгруппы": []
          }
        ]
      }
    ]
  },
  {
    "группа": "B63B  45/00",
    "расшифровка": "Размещение или приспосабливание  сигнальных или осветительных устройств на судах (спасательные буи, спасательные пояса, спасательные жилеты, костюмы и подобные им средства,\n            характеризующиеся средствами сигнализацииB63C   9/20) [4]",
    "подгруппы": [
      {
        "группа": "B63B  45/02",
        "расшифровка": "устройства для освещения водной поверхности впереди или вокруг судна",
        "подгруппы": []
      },
      {
        "группа": "B63B  45/04",
        "расшифровка": "судовые огни",
        "подгруппы": []
      },
      {
        "группа": "B63B  45/06",
        "расшифровка": "устройства для освещения палубы или внутренних помещений судов",
        "подгруппы": []
      },
      {
        "группа": "B63B  45/08",
        "расшифровка": "акустические устройства",
        "подгруппы": []
      }
    ]
  },
  {
    "группа": "B63B  49/00",
    "расшифровка": "Размещение морских инструментов и навигационных вспомогательных принадлежностей",
    "подгруппы": []
  },
  {
    "группа": "B63B  51/00",
    "расшифровка": "Обозначение навигационных путей иначе, чем с применением буев, бакенов [4]",
    "подгруппы": [
      {
        "группа": "B63B  51/02",
        "расшифровка": "с якорными плавучими маяками; с использованием маяков [4]",
        "подгруппы": []
      },
      {
        "группа": "B63B  51/04",
        "расшифровка": "с помощью свободно плавающих световых сигналов",
        "подгруппы": []
      }
    ]
  },
  {
    "группа": "B63B  57/00",
    "расшифровка": "Способы и устройства для очистки цистерн (танков), специально приспособленные для\n            судов",
    "подгруппы": [
      {
        "группа": "B63B  57/02",
        "расшифровка": "путем промывки",
        "подгруппы": []
      },
      {
        "группа": "B63B  57/04",
        "расшифровка": "путем вентиляции",
        "подгруппы": []
      }
    ]
  },
  {
    "группа": "B63B  59/00",
    "расшифровка": "Защита корпусов, специально предназначенная для  судов; устройства, специально предназначенные\n            для чистки судов",
    "подгруппы": [
      {
        "группа": "B63B  59/02",
        "расшифровка": "отбойные брусья, составляющие одно целое с плавучими средствами или специально предназначенные\n         для них; привальные брусья, обносные брусья, кранцы (отбойные брусья для спасательных шлюпокB63B  23/26)",
        "подгруппы": []
      },
      {
        "группа": "B63B  59/04",
        "расшифровка": "предотвращение обрастания корпуса [3]",
        "подгруппы": []
      },
      {
        "группа": "B63B  59/06",
        "расшифровка": "устройства для чистки корпусов [3]",
        "подгруппы": [
          {
            "группа": "B63B  59/08",
            "расшифровка": "подводных поверхностей корпусов судов, находящихся на плаву (59/10имеет преимущество) [3]",
            "подгруппы": []
          },
          {
            "группа": "B63B  59/10",
            "расшифровка": "с использованием крановых тележек или подобных средств,  приводимых в движение вдоль\n         поверхности [3]",
            "подгруппы": []
          }
        ]
      }
    ]
  },
  {
    "группа": "B63B  69/00",
    "расшифровка": "Оборудование для судов, не отнесённое к другим рубрикам МПК [2013.01]",
    "подгруппы": []
  },
  {
    "группа": "B63B  71/00",
    "расшифровка": "Проектирование судов; прогнозирование их рабочих характеристик [2020.01]",
    "подгруппы": [
      {
        "группа": "B63B  71/10",
        "расшифровка": "с использованием компьютерного моделирования, например метод конечных элементов [FEM]\n         или вычислительная гидродинамика [CFD] [2020.01]",
        "подгруппы": []
      },
      {
        "группа": "B63B  71/20",
        "расшифровка": "с использованием буксировочных резервуаров или испытательных бассейнов при проектировании\n         [2020.01]",
        "подгруппы": []
      }
    ]
  },
  {
    "группа": "B63B  73/00",
    "расшифровка": "Постройка или сборка судов или морских сооружений, например  корпусов судов или морских\n            платформ [2020.01]",
    "подгруппы": [
      {
        "группа": "B63B  73/10",
        "расшифровка": "постройка или сборка судов из предварительно изготовленных корпусных блоков, т.е.\n         полного набора поперечных секций корпусов [2020.01]",
        "подгруппы": []
      },
      {
        "группа": "B63B  73/20",
        "расшифровка": "постройка или сборка предварительно изготовленных  судовых модулей  или составных\n         частей, отличных от корпусных блоков, например машинных отделений, рулей, гребные\n         винтов, палубных надстроек, кают, трюмов или резервуаров [2020.01]",
        "подгруппы": []
      },
      {
        "группа": "B63B  73/30",
        "расшифровка": "перемещение или транспортирование модулей или корпусных блоков к местам сборки, например\n         с помощью перекатывания, подъёма или за счёт плавучести [2020.01]",
        "подгруппы": []
      },
      {
        "группа": "B63B  73/40",
        "расшифровка": "характеризующиеся способами соединения [2020.01]",
        "подгруппы": [
          {
            "группа": "B63B  73/43",
            "расшифровка": "сварка, например лазерная сварка  [2020.01]",
            "подгруппы": []
          },
          {
            "группа": "B63B  73/46",
            "расшифровка": "склеивание; обматывание лентой; холодная сварка [2020.01]",
            "подгруппы": []
          }
        ]
      },
      {
        "группа": "B63B  73/50",
        "расшифровка": "характеризующиеся способами штамповки, например изготовление изогнутых блоков [2020.01]",
        "подгруппы": []
      },
      {
        "группа": "B63B  73/60",
        "расшифровка": "характеризующиеся использованием специальных инструментов или оборудования; характеризующиеся\n         автоматизацией, например использованием роботов [2020.01]",
        "подгруппы": []
      },
      {
        "группа": "B63B  73/70",
        "расшифровка": "характеризующиеся использованием литейных форм; литейные формы или оправки для них\n         [2020.01]",
        "подгруппы": [
          {
            "группа": "B63B  73/72",
            "расшифровка": "характеризующиеся формованием пластиков, например инжекционное формование, экструзионное\n         формование или выдувное формование [2020.01]",
            "подгруппы": []
          },
          {
            "группа": "B63B  73/74",
            "расшифровка": "характеризующиеся послойным нанесением материалов [2020.01]",
            "подгруппы": []
          }
        ]
      }
    ]
  },
  {
    "группа": "B63B  75/00",
    "расшифровка": "Постройка или сборка плавучих морских сооружений, например полупогружных платформ,\n            платформ типа SPAR или платформ для ветроустановок [2020.01]",
    "подгруппы": []
  },
  {
    "группа": "B63B  77/00",
    "расшифровка": "Транспортирование или установка морских сооружений на месте с использованием сил плавучести,\n            например с использованием полупогружённых барж, загрузки балласта или транспортирования\n            нефтегазовых платформ [2020.01]",
    "подгруппы": [
      {
        "группа": "B63B  77/10",
        "расшифровка": "специально предназначенных для электростанций, например ветроустановок или приливно-отливных\n         турбинных генераторов [2020.01]",
        "подгруппы": []
      }
    ]
  },
  {
    "группа": "B63B  79/00",
    "расшифровка": "Мониторинг показателей или эксплуатационных параметров судов во время работы [2020.01]",
    "подгруппы": [
      {
        "группа": "B63B  79/10",
        "расшифровка": "с использованием датчиков, например датчиков давления, тензометров или акселерометров\n         [2020.01]",
        "подгруппы": [
          {
            "группа": "B63B  79/15",
            "расшифровка": "для мониторинга параметров окружающей среды, например высоты волны или погодных\n         данных [2020.01]",
            "подгруппы": []
          }
        ]
      },
      {
        "группа": "B63B  79/20",
        "расшифровка": "с использованием моделей или симуляции, например статистические модели или стохастические\n         модели [2020.01]",
        "подгруппы": []
      },
      {
        "группа": "B63B  79/30",
        "расшифровка": "для диагностирования, испытания или прогнозирования технического состояния или рабочих\n         характеристик судов [2020.01]",
        "подгруппы": []
      },
      {
        "группа": "B63B  79/40",
        "расшифровка": "для контролирования работы судов, например мониторинг их скорости, курса или графика\n         технического обслуживания [2020.01]",
        "подгруппы": []
      }
    ]
  },
  {
    "группа": "B63B  81/00",
    "расшифровка": "Ремонт или обслуживание судов [2020.01]",
    "подгруппы": []
  },
  {
    "группа": "B63B  83/00",
    "расшифровка": "Капитальный ремонт или переоборудование судов, например модернизации систем обработки\n            балластной воды  [2020.01]",
    "подгруппы": [
      {
        "группа": "B63B  83/10",
        "расшифровка": "для увеличения грузовой вместимости [2020.01]",
        "подгруппы": []
      },
      {
        "группа": "B63B  83/20",
        "расшифровка": "для использования по другому назначению, например для преобразования танкеров в объекты\n         FPSO-FLNG (FPSO - плавучая платформа для добычи, хранения и отгрузки нефти; FLNG -\n         плавучий завод для производства сжиженного природного газа)  [2020.01]",
        "подгруппы": []
      },
      {
        "группа": "B63B  83/30",
        "расшифровка": "для улучшения энергоэффективности, например с помощью улучшения гидродинамики или\n         модернизации энергетической установки [2020.01]",
        "подгруппы": []
      },
      {
        "группа": "B63B  83/40",
        "расшифровка": "для снижения рисков загрязненности и заражённости; для повышения безопасности \n         [2020.01]",
        "подгруппы": []
      }
    ]
  },
  {
    "группа": "B63B  85/00",
    "расшифровка": "Демонтаж или утилизация судов  [2020.01]",
    "подгруппы": []
  }
]